hurozo/__init__.py
hurozo/cli.py
hurozo/firebase.py
hurozo/data/nodes.json
hurozo-0.4.1.dist-info/METADATA
hurozo-0.4.1.dist-info/WHEEL
hurozo-0.4.1.dist-info/entry_points.txt
hurozo-0.4.1.dist-info/top_level.txt
hurozo-0.4.1.dist-info/RECORD
