Metadata-Version: 2.4
Name: hurozo
Version: 0.4.1
Summary: Hurozo Agentic Platform CLI
Author: Hurozo
Keywords: hurozo,agents,cli
Requires-Python: >=3.10
Requires-Dist: requests>=2.31.0
Requires-Dist: python-dotenv>=1.0.0
Requires-Dist: InquirerPy>=0.3.4
Requires-Dist: grpcio>=1.62.0
Requires-Dist: googleapis-common-protos>=1.63.0
Requires-Dist: python-webchannel>=0.1.0
